miniCPU/miniCPU.v
module miniCPU(
    input  wire CLK,
    input  wire RST_
);

    // Cycles
    localparam CY_RESET             = 6'h00; // CPU Reset
    localparam CY_FETCH_DECODE      = 6'h01; // Fetch and Decode
    localparam CY_GET_IMMEDIATE     = 6'h02; // Get an immediate operand (Constant)
    localparam CY_GET_OPERAND       = 6'h03; // Pick the address of the operand
    localparam CY_EXECUTE           = 6'h04; // Execute the instruction
    localparam CY_ILLEGAL_OPCODE    = 6'h3F; // Illegal (unknown) opcode fetched

    // Ocpodes
    localparam LDA_I                = 8'hA9;
    localparam LDA_M                = 8'hA5;
    localparam STA_M                = 8'h85;
    localparam ADC_I                = 8'h69;
    localparam ADC_M                = 8'h65;
    localparam NOP                  = 8'hEA;
    localparam JMP                  = 8'h4C;
    localparam JSR                  = 8'h20;
    localparam RTS                  = 8'h60;
    localparam PHA                  = 8'h48;
    localparam PLA                  = 8'h68;

	// Direction
	localparam dir_RM               = 2'b00;    // Register -> Memory
	localparam dir_MR               = 2'b01;    // Memory -> Register 
	localparam dir_CTRL             = 2'b10;    // Control Instruction (No Direction or stack based)

    // Registers (current state)
    reg[7:0]    A           = 8'd0;
    reg[7:0]    PC          = 8'd0;
    reg[7:0]    DP          = 8'd0;
    reg[7:0]    SP          = 8'd0;
    reg[7:0]    IR          = 8'd0;
    reg[7:0]    cycle       = CY_RESET;
    reg[7:0]    opcode      = 8'h00;

    // Registers (next state)
    reg[7:0]    A_out       = 8'd0;
    reg[7:0]    PC_out      = 8'd0;
    reg[7:0]    DP_out      = 8'd0;
    reg[7:0]    SP_out      = 8'd0;
    reg[7:0]    IR_out      = 8'd0;
    reg[7:0]    next_cycle  = CY_RESET;
    reg[7:0]    opcode_out  = 8'h00;

    // Instruction Table
    reg[7:0]    itable[0:255];
	reg[7:0]	instruction     = 8'd0;  // instruction record
	reg[7:0]	instruction_out = 8'd0;

	// Instruction fields
	`define 	direction			instruction[7:6]
	`define		cycle_start			instruction_out[5:0]

    // Memory
    reg[7:0]    mem[0:255];

    task execute_control();
    begin
        case(opcode)
            NOP: begin
                // Nothing to do 
            end
            // Return from subroutine
            RTS: begin
        		SP_out = SP + 8'd1;
                PC_out = mem[SP_out];
            end
            // Push Accumulator
            PHA: begin
                mem[SP] = A;
        		SP_out = SP - 8'd1;
            end
            // Pull Accumulator
            PLA: begin
        		SP_out = SP + 8'd1;
                A_out = mem[SP_out];
            end
        endcase
    end
    endtask

    task execute_memory_register();
    begin
        case(opcode)
            // Loads an immediate value to the accumulator
            LDA_I: begin
                A_out = IR;
            end
            // Loads a memory value to the accumulator
            LDA_M: begin
                A_out = mem[DP];
            end
            // Jumps to a new location
            JMP: begin
                PC_out = IR;
            end
            // Adds a constant to the accumulator
            ADC_I: begin
                A_out = A + IR;
            end
            // Adds a memory value to the accumulator
            ADC_M: begin
                A_out = A + mem[DP];
            end
            // Jump to subroutine
            JSR: begin
                mem[SP] = PC + 8'd1; // Push return address (PC + 1)
        		SP_out = SP - 8'd1;  // Decrements the Stack Pointer
                PC_out = IR;         // Loads the new address
            end
        endcase
    end
    endtask

    task execute_register_memory();
    begin
        case(opcode)
            // Store the accumulator in the memory
            STA_M: begin
                mem[DP] = A;
            end
        endcase
    end
    endtask

    always @(posedge CLK) 
    begin
        if (!RST_)
            cycle <= CY_RESET;
        else
            cycle <= next_cycle;
        // Next
        A <= A_out;
        PC <= PC_out;
        DP <= DP_out;
        SP <= SP_out;
        IR <= IR_out;
        opcode <= opcode_out;
        instruction <= instruction_out;
    end

    always @(*) 
    begin
        // Current
        next_cycle = cycle;
        A_out = A;
        PC_out = PC;
        DP_out = DP;
        SP_out = SP;
        IR_out = IR;
        opcode_out = opcode;
        instruction_out = instruction;
        // Cycle shift
        case (cycle)
            CY_RESET: begin
                if (RST_) begin // Waits until RST_ is high again
                    // Registers initialization
                    SP_out = 8'hFF;
                    A_out  = 8'h00;
                    PC_out = 8'h00;
                    DP_out = 8'h00;
                    // Jump to the first Fetch
                    next_cycle = CY_FETCH_DECODE;    
                end
            end
            CY_FETCH_DECODE: begin
                // Fetch
                opcode_out = mem[PC];
                // Decode (get Instruction Info)
                instruction_out = itable[opcode_out];
                // Increment PC for pointing to the next byte
                PC_out = PC + 8'd1;
                // Jumps to the first Instruction sequence step
                next_cycle = `cycle_start;
            end
            CY_GET_OPERAND: begin
                DP_out = mem[PC];     // Get the address of the operand
                next_cycle = CY_EXECUTE;
            end
            CY_GET_IMMEDIATE: begin
                IR_out = mem[PC];
                next_cycle = CY_EXECUTE;
            end
            CY_EXECUTE: begin
                case(`direction)
                    dir_CTRL: execute_control();
                    dir_MR: begin
                        PC_out = PC + 8'd1;
                        execute_memory_register();
                    end
                    dir_RM: begin
                        PC_out = PC + 8'd1;
                        execute_register_memory();
                    end
                endcase
                next_cycle = CY_FETCH_DECODE; // On the road again...
            end
            CY_ILLEGAL_OPCODE: begin
                next_cycle = CY_ILLEGAL_OPCODE; // stay here forever
            end
            default: // just to avoid compiler warnings
                next_cycle = CY_ILLEGAL_OPCODE; 
        endcase
    end
    
    integer i;
    initial begin
        // Clears the instruction Table and the memory
        for (i = 0; i < 256; i = i + 1) begin
                itable[i] = {2'b00, CY_ILLEGAL_OPCODE};           
                mem[i] = 8'h00;
        end   
        // Init the instruction Table
        itable[LDA_I] = {dir_MR,   CY_GET_IMMEDIATE};
        itable[LDA_M] = {dir_MR,   CY_GET_OPERAND};
        itable[STA_M] = {dir_RM,   CY_GET_OPERAND};
        itable[ADC_I] = {dir_MR,   CY_GET_IMMEDIATE};
        itable[ADC_M] = {dir_MR,   CY_GET_OPERAND};
        itable[NOP  ] = {dir_CTRL, CY_EXECUTE};
        itable[JMP  ] = {dir_MR,   CY_GET_IMMEDIATE};
        itable[JSR  ] = {dir_MR,   CY_GET_IMMEDIATE};
        itable[RTS  ] = {dir_CTRL, CY_EXECUTE};
        itable[PHA  ] = {dir_CTRL, CY_EXECUTE};
        itable[PLA  ] = {dir_CTRL, CY_EXECUTE};
        //-----------------------------------------------------
        // A small program to test all the instructions
        //-----------------------------------------------------
        //                          checkpoint
        // Load 4F in A             
        mem[8'h00] = LDA_I;        
        mem[8'h01] = 8'h4F;         // A = 4F 
        // Store A in $21
        mem[8'h02] = STA_M;         
        mem[8'h03] = 8'h21;       
        // Clear A
        mem[8'h04] = LDA_I;
        mem[8'h05] = 8'h00;         // A = 00
        // Load $21 in A to verify the previous store
        mem[8'h06] = LDA_M;
        mem[8'h07] = 8'h21;         // A = 4F
        // ADC $21 to A 
        mem[8'h08] = ADC_M;
        mem[8'h09] = 8'h21;         // A = 9E
        // ADC #$01 to A 
        mem[8'h0A] = ADC_I;
        mem[8'h0B] = 8'h01;         // A = 9F
                                    
        // JSR $80 
        mem[8'h0C] = JSR;
        mem[8'h0D] = 8'h80;         // PC = 80
        // Push A
        mem[8'h0E] = PHA;
        // Clear A
        mem[8'h0F] = LDA_I;
        mem[8'h10] = 8'h00;         // A = 00
        // JMP $85
        mem[8'h11] = JMP;
        mem[8'h12] = 8'h85;         // A = 00

        mem[8'h80] = LDA_I;
        mem[8'h81] = 8'hFF;
        mem[8'h82] = RTS;
                                    // PC = 0E

        mem[8'h85] = PLA;           // A = FF
        mem[8'h86] = NOP;           // <- The execution stops here due to 
                                    //    illegal opcode (00) in $87

    end
endmodule

miniCPU/miniCPU_tb.v
`timescale 10ns/10ps
`include "miniCPU.v" 
module miniCPU_tb;

	reg clk;
	reg rst_;

	always 
		#1 clk = ~clk; // Clock generation

    // mini-CPU instance
    miniCPU CPU(
        .CLK(clk),
        .RST_(rst_)
    );

	initial begin
        $dumpfile("signals.vcd"); // Name of the signal dump file
        $dumpvars(0, miniCPU_tb); // Signals to dump
		clk     = 1'b0; // *Everything* must be inited in a testbench
		rst_    = 1'b0;
		#2 rst_ = 1'b1; // Reset remains LOW for two time units
        #85; // Wait 85 time units (meanwhile the clock is running)
        $finish(); 
	end

endmodule

miniCPU/signals.vcd
$date
	Fri Feb 09 17:57:39 2024
$end
$version
	Icarus Verilog
$end
$timescale
	10ps
$end
$scope module miniCPU_tb $end
$var reg 1 ! clk $end
$var reg 1 " rst_ $end
$scope module CPU $end
$var wire 1 ! CLK $end
$var wire 1 " RST_ $end
$var parameter 8 # ADC_I $end
$var parameter 8 $ ADC_M $end
$var parameter 6 % CY_EXECUTE $end
$var parameter 6 & CY_FETCH_DECODE $end
$var parameter 6 ' CY_GET_IMMEDIATE $end
$var parameter 6 ( CY_GET_OPERAND $end
$var parameter 6 ) CY_ILLEGAL_OPCODE $end
$var parameter 6 * CY_RESET $end
$var parameter 8 + JMP $end
$var parameter 8 , JSR $end
$var parameter 8 - LDA_I $end
$var parameter 8 . LDA_M $end
$var parameter 8 / NOP $end
$var parameter 8 0 PHA $end
$var parameter 8 1 PLA $end
$var parameter 8 2 RTS $end
$var parameter 8 3 STA_M $end
$var parameter 2 4 dir_CTRL $end
$var parameter 2 5 dir_MR $end
$var parameter 2 6 dir_RM $end
$var reg 8 7 A [7:0] $end
$var reg 8 8 A_out [7:0] $end
$var reg 8 9 DP [7:0] $end
$var reg 8 : DP_out [7:0] $end
$var reg 8 ; IR [7:0] $end
$var reg 8 < IR_out [7:0] $end
$var reg 8 = PC [7:0] $end
$var reg 8 > PC_out [7:0] $end
$var reg 8 ? SP [7:0] $end
$var reg 8 @ SP_out [7:0] $end
$var reg 8 A cycle [7:0] $end
$var reg 8 B instruction [7:0] $end
$var reg 8 C instruction_out [7:0] $end
$var reg 8 D next_cycle [7:0] $end
$var reg 8 E opcode [7:0] $end
$var reg 8 F opcode_out [7:0] $end
$var integer 32 G i [31:0] $end
$scope task execute_control $end
$upscope $end
$scope task execute_memory_register $end
$upscope $end
$scope task execute_register_memory $end
$upscope $end
$upscope $end
$upscope $end
$enddefinitions $end
$comment Show the parameter values. $end
$dumpall
b0 6
b1 5
b10 4
b10000101 3
b1100000 2
b1101000 1
b1001000 0
b11101010 /
b10100101 .
b10101001 -
b100000 ,
b1001100 +
b0 *
b111111 )
b11 (
b10 '
b1 &
b100 %
b1100101 $
b1101001 #
$end
#0
$dumpvars
b100000000 G
b0 F
b0 E
b0 D
b0 C
b0 B
b0 A
b0 @
b0 ?
b0 >
b0 =
b0 <
b0 ;
b0 :
b0 9
b0 8
b0 7
0"
0!
$end
#1000
1!
#2000
b1 D
b11111111 @
0!
1"
#3000
b10 D
b1 >
b1000010 C
b10101001 F
b11111111 ?
b1 A
1!
#4000
0!
#5000
b100 D
b1001111 <
b1000010 B
b10101001 E
b1 =
b10 A
1!
#6000
0!
#7000
b1 D
b1001111 8
b10 >
b1001111 ;
b100 A
1!
#8000
0!
#9000
b11 D
b11 >
b11 C
b10000101 F
b10 =
b1001111 7
b1 A
1!
#10000
0!
#11000
b100 D
b100001 :
b11 B
b10000101 E
b11 =
b11 A
1!
#12000
0!
#13000
b1 D
b100 >
b100001 9
b100 A
1!
#14000
0!
#15000
b10 D
b101 >
b1000010 C
b10101001 F
b100 =
b1 A
1!
#16000
0!
#17000
b100 D
b0 <
b1000010 B
b10101001 E
b101 =
b10 A
1!
#18000
0!
#19000
b1 D
b0 8
b110 >
b0 ;
b100 A
1!
#20000
0!
#21000
b11 D
b111 >
b1000011 C
b10100101 F
b110 =
b0 7
b1 A
1!
#22000
0!
#23000
b100 D
b1000011 B
b10100101 E
b111 =
b11 A
1!
#24000
0!
#25000
b1 D
b1001111 8
b1000 >
b100 A
1!
#26000
0!
#27000
b11 D
b1001 >
b1100101 F
b1000 =
b1001111 7
b1 A
1!
#28000
0!
#29000
b100 D
b1100101 E
b1001 =
b11 A
1!
#30000
0!
#31000
b1 D
b10011110 8
b1010 >
b100 A
1!
#32000
0!
#33000
b10 D
b1011 >
b1000010 C
b1101001 F
b1010 =
b10011110 7
b1 A
1!
#34000
0!
#35000
b100 D
b1 <
b1000010 B
b1101001 E
b1011 =
b10 A
1!
#36000
0!
#37000
b1 D
b10011111 8
b1100 >
b1 ;
b100 A
1!
#38000
0!
#39000
b10 D
b1101 >
b100000 F
b1100 =
b10011111 7
b1 A
1!
#40000
0!
#41000
b100 D
b10000000 <
b100000 E
b1101 =
b10 A
1!
#42000
0!
#43000
b1 D
b11111110 @
b10000000 >
b10000000 ;
b100 A
1!
#44000
0!
#45000
b10 D
b10000001 >
b10101001 F
b11111110 ?
b10000000 =
b1 A
1!
#46000
0!
#47000
b100 D
b11111111 <
b10101001 E
b10000001 =
b10 A
1!
#48000
0!
#49000
b1 D
b11111111 8
b10000010 >
b11111111 ;
b100 A
1!
#50000
0!
#51000
b100 D
b10000011 >
b10000100 C
b1100000 F
b10000010 =
b11111111 7
b1 A
1!
#52000
0!
#53000
b1 D
b1110 >
b11111111 @
b10000100 B
b1100000 E
b10000011 =
b100 A
1!
#54000
0!
#55000
b100 D
b1111 >
b1001000 F
b11111111 ?
b1110 =
b1 A
1!
#56000
0!
#57000
b1 D
b11111110 @
b1001000 E
b1111 =
b100 A
1!
#58000
0!
#59000
b10 D
b10000 >
b1000010 C
b10101001 F
b11111110 ?
b1 A
1!
#60000
0!
#61000
b100 D
b0 <
b1000010 B
b10101001 E
b10000 =
b10 A
1!
#62000
0!
#63000
b1 D
b0 8
b10001 >
b0 ;
b100 A
1!
#64000
0!
#65000
b10 D
b10010 >
b1001100 F
b10001 =
b0 7
b1 A
1!
#66000
0!
#67000
b100 D
b10000101 <
b1001100 E
b10010 =
b10 A
1!
#68000
0!
#69000
b1 D
b10000101 >
b10000101 ;
b100 A
1!
#70000
0!
#71000
b100 D
b10000110 >
b10000100 C
b1101000 F
b10000101 =
b1 A
1!
#72000
0!
#73000
b1 D
b11111111 8
b11111111 @
b10000100 B
b1101000 E
b10000110 =
b100 A
1!
#74000
0!
#75000
b100 D
b10000111 >
b11101010 F
b11111111 ?
b11111111 7
b1 A
1!
#76000
0!
#77000
b1 D
b11101010 E
b10000111 =
b100 A
1!
#78000
0!
#79000
b111111 D
b10001000 >
b111111 C
b0 F
b1 A
1!
#80000
0!
#81000
b111111 B
b0 E
b10001000 =
b111111 A
1!
